lammps_manylinux_2_28.libs/libmpi-aca79bf7.so.12.1.11
lammps_manylinux_2_28.libs/libgomp-1e1b248e.so.1.0.0
lammps_manylinux_2_28.libs/libgfortran-f103c419.so.5.0.0
lammps_manylinux_2_28.libs/libhwloc-898b3d19.so.15.2.0
lammps_manylinux_2_28.libs/libquadmath-a8911d2c.so.0.0.0
lammps_manylinux_2_28.libs/libmpicxx-8f050645.so.12.1.11
lammps_manylinux_2_28.libs/libjpeg-4cc660e3.so.62.2.0
lammps_manylinux_2_28.libs/libpng16-b53259c8.so.16.34.0
lammps_manylinux_2_28-2022.6.23.4.0.dist-info/METADATA
lammps_manylinux_2_28-2022.6.23.4.0.dist-info/entry_points.txt
lammps_manylinux_2_28-2022.6.23.4.0.dist-info/RECORD
lammps_manylinux_2_28-2022.6.23.4.0.dist-info/WHEEL
lammps/executable.py
lammps/binary2txt
lammps/micelle2d.x
lammps/formats.py
lammps/chain.x
lammps/data.py
lammps/liblammps.so.0
lammps/core.py
lammps/pylammps.py
lammps/numpy_wrapper.py
lammps/lmp
lammps/msi2lmp
lammps/__init__.py
lammps/stl_bin2txt
lammps/liblammps.so
lammps/constants.py
lammps/include/lammps/library.h
lammps/include/lammps/kspace.h
lammps/include/lammps/pair.h
lammps/include/lammps/input.h
lammps/include/lammps/platform.h
lammps/include/lammps/pointers.h
lammps/include/lammps/region.h
lammps/include/lammps/citeme.h
lammps/include/lammps/improper.h
lammps/include/lammps/atom.h
lammps/include/lammps/lmptype.h
lammps/include/lammps/variable.h
lammps/include/lammps/error.h
lammps/include/lammps/compute.h
lammps/include/lammps/fix.h
lammps/include/lammps/angle.h
lammps/include/lammps/modify.h
lammps/include/lammps/neigh_list.h
lammps/include/lammps/utils.h
lammps/include/lammps/info.h
lammps/include/lammps/lmppython.h
lammps/include/lammps/dihedral.h
lammps/include/lammps/update.h
lammps/include/lammps/timer.h
lammps/include/lammps/command.h
lammps/include/lammps/neighbor.h
lammps/include/lammps/bond.h
lammps/include/lammps/lammps.h
lammps/include/lammps/output.h
lammps/include/lammps/domain.h
lammps/include/lammps/group.h
lammps/include/lammps/exceptions.h
lammps/include/lammps/memory.h
lammps/include/lammps/lattice.h
lammps/include/lammps/comm.h
lammps/include/lammps/universe.h
lammps/include/lammps/force.h
lammps/include/lammps/fmt/core.h
