Metadata-Version: 2.1
Name: lammps-manylinux-2-28
Version: 2022.6.23.4.0
Summary: unoffical LAMMPS Molecular Dynamics Python package
Keywords: lammps
Author-Email: The LAMMPS Developers <developers@lammps.org>, Jinzhe Zeng <jinzhe.zeng@rutgers.edu>
License: GNU GENERAL PUBLIC LICENSE
Classifier: Programming Language :: Python :: 3
Classifier: Development Status :: 5 - Production/Stable
Classifier: Environment :: Console
Classifier: License :: OSI Approved :: GNU General Public License v2 (GPLv2)
Classifier: Operating System :: OS Independent
Project-URL: Repository, https://github.com/njzjz/lammps-wheel
Project-URL: Lammps_repository, https://github.com/lammps/lammps
Project-URL: Lammps_documentation, https://docs.lammps.org/
Requires-Python: >=3.7
Requires-Dist: importlib_metadata>=1.4; python_version < "3.8"
